[
    {
        "product": "Versa Toque - 100% Merino Wool - 0  ( 22\"-24\" circumference )",
        "sku": "KY050-VT0",
        "quantity": "1",
        "price": "64.00"
    },
    {
        "product": "Versa Toque - 100% Merino Wool - +  ( 23\" - 25\" circumference )",
        "sku": "KY050-VTL",
        "quantity": "1",
        "price": "64.00"
    }
][
{"product": "Versa Toque - 100% Merino Wool - 0  ( 22\"-24\" circumference )", "sku": "KY050-VT0", "quantity": "1", "price": "64.00"},
{"product": "Versa Toque - 100% Merino Wool - +  ( 23\" - 25\" circumference )", "sku": "KY050-VTL", "quantity": "1", "price": "64.00"}
][
{"product": "Versa Toque - 100% Merino Wool - 0  ( 22\"-24\" circumference )", "sku": "KY050-VT0", "quantity": "1", "price": "64.00"},
{"product": "Versa Toque - 100% Merino Wool - +  ( 23\" - 25\" circumference )", "sku": "KY050-VTL", "quantity": "1", "price": "64.00"}
]